MANIFEST.in
NOTICE
setup.py
scripts/snmp_exporter
snmp_exporter/__init__.py
snmp_exporter/collector.py
snmp_exporter/http.py
snmp_exporter.egg-info/PKG-INFO
snmp_exporter.egg-info/SOURCES.txt
snmp_exporter.egg-info/dependency_links.txt
snmp_exporter.egg-info/requires.txt
snmp_exporter.egg-info/top_level.txt