Metadata-Version: 1.1
Name: snmp-exporter
Version: 0.0.5
Summary: SNMP exporter for the Prometheus monitoring system.
Home-page: https://github.com/prometheus/snmp_exporter
Author: Brian Brazil
Author-email: brian.brazil@robustperception.io
License: Apache Software License 2.0
Keywords: prometheus exporter network monitoring snmp
Platform: UNKNOWN
Classifier: Development Status :: 3 - Alpha
Classifier: Intended Audience :: Information Technology
Classifier: Intended Audience :: System Administrators
Classifier: Topic :: System :: Monitoring
Classifier: Topic :: System :: Networking :: Monitoring
Classifier: License :: OSI Approved :: Apache Software License
